connectivly/__init__.py
connectivly-0.1.0.dist-info/LICENSE
connectivly-0.1.0.dist-info/METADATA
connectivly-0.1.0.dist-info/WHEEL
connectivly-0.1.0.dist-info/top_level.txt
connectivly-0.1.0.dist-info/RECORD
