Metadata-Version: 2.1
Name: connectivly
Version: 0.1.0
Summary: Python library for the Connectivly API
Author: Hotswap
Author-email: team@hotswap.app
License-File: LICENSE
Requires-Dist: requests
Requires-Dist: PyJWT
Requires-Dist: python-jose[cryptography]
